odoo/addons/hotel_housekeeping_planning/README.rst
odoo/addons/hotel_housekeeping_planning/__init__.py
odoo/addons/hotel_housekeeping_planning/__manifest__.py
odoo/addons/hotel_housekeeping_planning/i18n/hotel_housekeeping_planning.pot
odoo/addons/hotel_housekeeping_planning/models/__init__.py
odoo/addons/hotel_housekeeping_planning/models/hotel_reservation.py
odoo/addons/hotel_housekeeping_planning/models/hotel_room.py
odoo/addons/hotel_housekeeping_planning/readme/CONTRIBUTORS.rst
odoo/addons/hotel_housekeeping_planning/readme/DESCRIPTION.rst
odoo/addons/hotel_housekeeping_planning/reports/housekeeping_planning.xml
odoo/addons/hotel_housekeeping_planning/reports/reports.xml
odoo/addons/hotel_housekeeping_planning/static/description/icon.png
odoo/addons/hotel_housekeeping_planning/static/description/index.html
odoo/addons/hotel_housekeeping_planning/tests/__init__.py
odoo/addons/hotel_housekeeping_planning/tests/test_hotel_housekeeping_planning.py
odoo/addons/hotel_housekeeping_planning/views/hotel_reservation.xml
odoo11_addon_hotel_housekeeping_planning-11.0.1.0.0.99.dev10.dist-info/METADATA
odoo11_addon_hotel_housekeeping_planning-11.0.1.0.0.99.dev10.dist-info/WHEEL
odoo11_addon_hotel_housekeeping_planning-11.0.1.0.0.99.dev10.dist-info/top_level.txt
odoo11_addon_hotel_housekeeping_planning-11.0.1.0.0.99.dev10.dist-info/RECORD
